Workbook

Sheet Lista de Materiais
A1: Lista de Materiais — Rede Wi-Fi, CFTV e Cabeamento Estruturado
A2: Projeto: Residência Swiss J26 (Patrick de Freitas Alves) — Quadra J, Lote 26, Condomínio Swiss Parque, Rio Branco/AC
A3: Base: escopo-rede-wifi-cftv-cabeamento.md — preencher coluna "Preço Unitário" (célula amarela) com cotação real antes de fechar orçamento.
A5: Nº | B5: Categoria | C5: Item | D5: Especificação / Modelo sugerido | E5: Local / Ponto | F5: Qtde | G5: Un. | H5: Preço Unit. (R$) | I5: Preço Total (R$) | J5: Observações
A6: 1 | B6: Wi-Fi | C6: Access Point Wi-Fi 6 indoor (teto) | D6: UniFi U6-Lite ou equivalente, dual-band, PoE | E6: Living / Circulação | F6: 1 | G6: un | I6: =IF(H6="","",F6*H6) | J6: AP-01 — cabeamento dedicado
A7: 2 | B7: Wi-Fi | C7: Access Point Wi-Fi 6 indoor (teto) | D7: UniFi U6-Lite ou equivalente, dual-band, PoE | E7: Corredor das Suítes | F7: 1 | G7: un | I7: =IF(H7="","",F7*H7) | J7: AP-02 — cabeamento dedicado
A8: 3 | B8: Wi-Fi | C8: Access Point Wi-Fi 6 externo IP65 (com suporte de fixação) | D8: UniFi U6-Mesh ou equivalente, PoE | E8: Área Gourmet / Deck | F8: 1 | G8: un | I8: =IF(H8="","",F8*H8) | J8: AP-03 — sob projeção do beiral
A9: 4 | B9: Wi-Fi | C9: Access Point Wi-Fi 6 externo IP65 (com suporte de fixação) | D9: UniFi U6-Mesh ou equivalente, PoE | E9: Garagem | F9: 1 | G9: un | I9: =IF(H9="","",F9*H9) | J9: AP-04 — item opcional, confirmar com o cliente
A10: 5 | B10: CFTV | C10: Câmera Ubiquiti UniFi Protect G5 Dome | D10: 5MP, IR ~30m, H.265, IP67, PoE 802.3af | E10: Muros e cantos do lote | F10: 6 | G10: un | I10: =IF(H10="","",F10*H10) | J10: CAM-01 a CAM-06 — mesmo modelo em todas as posições; ajustar máscara de privacidade em CAM-01 e CAM-06 (cantos)
A11: 6 | B11: CFTV | C11: UniFi Protect Console (UNVR ou Dream Machine Pro/SE) + HD 6TB | D11: Compressão H.265, gravação por movimento, retenção ~30-45 dias | E11: Escritório | F11: 1 | G11: un | I11: =IF(H11="","",F11*H11) | J11: Câmeras UniFi Protect exigem console UniFi OS, não um NVR ONVIF genérico. Upgrade opcional: 2x4TB em RAID1
A12: 7 | B12: CFTV | C12: Caixa de passagem externa IP65 (câmeras/AP externo) | D12: Para folga e emenda de cabo PoE | E12: Perímetro externo | F12: 4 | G12: un | I12: =IF(H12="","",F12*H12) | J12: —
A13: 8 | B13: Infraestrutura Passiva | C13: Rack de parede 9U–12U completo | D13: Gabinete fechado com porta ventilada + patch panel Cat6 24 portas + organizador de cabos + régua de tomadas | E13: Escritório | F13: 1 | G13: kit | I13: =IF(H13="","",F13*H13) | J13: Ambiente de permanência — priorizar modelo silencioso
A14: 9 | B14: Infraestrutura Passiva | C14: Switch PoE+ gerenciável 24 portas | D14: Budget PoE compatível com 4 APs + 6 câmeras, com suporte a VLANs | E14: Escritório | F14: 1 | G14: un | I14: =IF(H14="","",F14*H14) | J14: —
A15: 10 | B15: Infraestrutura Passiva | C15: Nobreak 1kVA | D15: Para o rack e o roteador de borda | E15: Escritório | F15: 1 | G15: un | I15: =IF(H15="","",F15*H15) | J15: Circuito elétrico dedicado recomendado
A16: 11 | B16: Cabeamento Estruturado | C16: Cabo Cat6 U/UTP — caixa 305m | D16: Uso interno, PoE-rated | E16: Backbone geral (a partir do Escritório) | F16: ='Memória de Cálculo'!B11 -> 1 | G16: cx | I16: =IF(H16="","",F16*H16) | J16: Atende os 16 pontos de rede (4 Wi-Fi + 6 CFTV + 6 TV) mais o uplink da ONU, já com margem de instalação — quantidade calculada na aba Memória de Cálculo
A17: 12 | B17: Cabeamento Estruturado | C17: Kit de terminação dos pontos de rede | D17: 18 keystone jacks Cat6 + 6 espelhos/placas 4x2 c/ saída RJ45 + 18 conectores RJ45 + 18 patch cords Cat6 | E17: 16 pontos de rede (TVs/APs/câmeras) | F17: 1 | G17: kit | I17: =IF(H17="","",F17*H17) | J17: —
A18: 13 | B18: Cabeamento Estruturado | C18: Kit de infraestrutura de passagem | D18: 10 caixas de passagem 4x4 embutidas + 3 rolos (50m) de eletroduto corrugado reforçado 3/4" | E18: Backbone geral (Circulação) | F18: 1 | G18: kit | I18: =IF(H18="","",F18*H18) | J18: —
A19: 14 | B19: Serviços (opcional) | C19: Instalação, configuração e comissionamento | D19: Mão de obra — passagem de cabos, fixação, configuração de VLANs/SSIDs, testes | E19: Geral | F19: 1 | G19: vb | I19: =IF(H19="","",F19*H19) | J19: Fora do escopo de materiais — valor conforme prestador de serviço
C21: TOTAL GERAL (materiais com preço informado) | I21: =SUM(I6:I19) -> 0
A23: Nota: preços não pesquisados nesta etapa de escopo. Células amarelas (Preço Unit.) devem ser preenchidas com cotação real do integrador/fornecedor antes de fechar orçamento.

Sheet Resumo por Categoria
A1: Resumo por Categoria
A3: Categoria | B3: Qtde de Itens | C3: Total (R$)
A4: Wi-Fi | B4: =COUNTIF('Lista de Materiais'!$B$6:$B$19,A4) -> 4 | C4: =SUMIF('Lista de Materiais'!$B$6:$B$19,A4,'Lista de Materiais'!$I$6:$I$19) -> 0
A5: CFTV | B5: =COUNTIF('Lista de Materiais'!$B$6:$B$19,A5) -> 3 | C5: =SUMIF('Lista de Materiais'!$B$6:$B$19,A5,'Lista de Materiais'!$I$6:$I$19) -> 0
A6: Cabeamento Estruturado | B6: =COUNTIF('Lista de Materiais'!$B$6:$B$19,A6) -> 3 | C6: =SUMIF('Lista de Materiais'!$B$6:$B$19,A6,'Lista de Materiais'!$I$6:$I$19) -> 0
A7: Infraestrutura Passiva | B7: =COUNTIF('Lista de Materiais'!$B$6:$B$19,A7) -> 3 | C7: =SUMIF('Lista de Materiais'!$B$6:$B$19,A7,'Lista de Materiais'!$I$6:$I$19) -> 0
A8: Serviços (opcional) | B8: =COUNTIF('Lista de Materiais'!$B$6:$B$19,A8) -> 1 | C8: =SUMIF('Lista de Materiais'!$B$6:$B$19,A8,'Lista de Materiais'!$I$6:$I$19) -> 0
A10: TOTAL GERAL | C10: =SUM(C4:C8) -> 0

Sheet Mapa de Pontos por Ambiente
A1: Mapa de Pontos por Ambiente — referência do escopo técnico
A2: Complementa a Lista de Materiais mostrando onde cada ponto ativo fica fisicamente.
A4: Ambiente | B4: Ponto Wi-Fi (AP) | C4: Câmera CFTV nas proximidades | D4: Ponto de TV (RJ45) | E4: Observação
A5: Living | B5: AP-01 | C5: — | D5: 1x | E5: Ponto principal
A6: Cozinha/Jantar | B6: AP-01 (cobertura estendida) | C6: — | D6: — | E6: —
A7: Escritório | B7: AP-01 | C7: CAM-06 (cobertura estendida, canto SO) | D7: 1x | E7: Rack instalado neste ambiente (patch direto)
A8: Suíte Master + Closet | B8: AP-02 (cobertura estendida) | C8: CAM-02 e CAM-03 (nicho BWC e recuo lateral oeste) | D8: 1x | E8: Ponto mais distante do rack (~26-29m)
A9: Suíte 01 | B9: AP-02 | C9: CAM-04 (posição central) | D9: 1x | E9: —
A10: Suíte 02 | B10: AP-02 | C10: CAM-04 e CAM-05 (central e muro leste/pátio) | D10: 1x | E10: —
A11: Área Gourmet + Deck | B11: AP-03 | C11: CAM-01 (canto noroeste) | D11: 1x | E11: Ponto externo coberto pelo beiral
A12: Piscina | B12: AP-03 (cobertura estendida) | C12: CAM-01 (canto noroeste) | D12: — | E12: Sem equipamentos elétricos na borda molhada
A13: Garagem | B13: AP-04 (opcional, externo) | C13: CAM-06 (canto sudoeste) | D13: — | E13: Entrada da ONU da operadora; acesso de pedestres (canto sudeste) sem câmera dedicada — ver item 4.1
A14: Depósito / Lavanderia / Secagem | B14: AP-01 (cobertura estendida) | C14: CAM-06 (cobertura estendida) | D14: — | E14: —

Sheet Memória de Cálculo
A1: Memória de Cálculo — Metragem de Cabo Cat6
A2: Fonte: escopo-rede-wifi-cftv-cabeamento.md, itens 5, 6.1 e 9 (estimativas de escopo, a validar em campo).
A4: Componente | B4: Valor | C4: Unidade | D4: Observação
A5: Wi-Fi — 4 pontos (AP-01, AP-02, AP-03 e AP-04 opcional) | B5: 45 | C5: m | D5: Distância-base ~39m + margem de instalação
A6: CFTV — 6 pontos (CAM-01 a CAM-06) | B6: 70 | C6: m | D6: Distância-base ~61m + margem de instalação
A7: TV — 6 pontos (Living, Suíte Master, Suíte 01, Suíte 02, Escritório, Gourmet) | B7: 60 | C7: m | D7: Distância-base ~52m + margem de instalação
A8: Uplink ONU (Garagem) → Rack (Escritório) | B8: 10 | C8: m | D8: Distância-base ~6-8m + margem de instalação
A10: TOTAL DE CABO CAT6 A COMPRAR | B10: =SUM(B5:B8) -> 185 | C10: m
A11: Caixas de cabo Cat6 necessárias (305m cada) | B11: =ROUNDUP(B10/305,0) -> 1 | C11: cx | D11: Puxado automaticamente para a Lista de Materiais
A12: Folga restante após atender todos os pontos | B12: =B11*305-B10 -> 120 | C12: m | D12: Margem para ajustes de rota em campo
